bliss/__init__.py
bliss/api.py
bliss/catalog.py
bliss/conf/__init__.py
bliss/conf/base_config.yaml
bliss/conf/igs.py
bliss/encoder.py
bliss/generate.py
bliss/metrics.py
bliss/plotting.py
bliss/predict.py
bliss/simulator/__init__.py
bliss/simulator/background.py
bliss/simulator/decoder.py
bliss/simulator/prior.py
bliss/simulator/simulated_dataset.py
bliss/surveys/__init__.py
bliss/surveys/decals.py
bliss/surveys/hst.py
bliss/surveys/lsst.py
bliss/surveys/sdss.py
bliss/train.py
bliss/unconstrained_dists.py
bliss/utils/__init__.py
bliss/utils/download_utils.py
bliss_deblender-0.2.1.dist-info/LICENSE.md
bliss_deblender-0.2.1.dist-info/METADATA
bliss_deblender-0.2.1.dist-info/WHEEL
bliss_deblender-0.2.1.dist-info/entry_points.txt
bliss_deblender-0.2.1.dist-info/RECORD
