Metadata-Version: 2.1
Name: bliss-deblender
Version: 0.2.1
Summary: Bayesian Light Source Separator
Home-page: https://github.com/prob-ml/bliss
License: MIT
Keywords: cosmology,blending,weak lensing,bayesian,ml,pytorch
Author: Ismael Mendoza
Author-email: imendoza@umich.edu
Requires-Python: >=3.10,<4.0
Classifier: License :: OSI Approved :: MIT License
Classifier: Programming Language :: Python :: 3
Classifier: Programming Language :: Python :: 3.10
Classifier: Programming Language :: Python :: 3.11
Requires-Dist: astropy (>=4.2.1)
Requires-Dist: bokeh (>=3.1.1,<4.0.0)
Requires-Dist: einops (>=0.3.0)
Requires-Dist: galsim (>=2.2.4)
Requires-Dist: hydra-core (>=1.0.4)
Requires-Dist: matplotlib (>=3.3.3)
Requires-Dist: numpy (>=1.18.5)
Requires-Dist: pytorch-lightning (>=1.9)
Requires-Dist: requests (>=2.31.0,<3.0.0)
Requires-Dist: scikit-image (>=0.20.0)
Requires-Dist: scikit-learn (>=0.24.2)
Requires-Dist: scipy (>=1.4.1)
Requires-Dist: torch (>=1.9)
Requires-Dist: torchmetrics (>=0.5.1)
Requires-Dist: yolov5 (>=7.0.9,<8.0.0)
Project-URL: Documentation, https://prob-ml.github.io/bliss/
Project-URL: Repository, https://github.com/prob-ml/bliss
